{
    "asset":{
        "generatetool":"cesiumlab@www.cesiumlab.com",
        "gltfUpAxis":"Z",
        "version":"1.0"
    },
    "root":{
        "boundingVolume":{
            "box":[
                -6.98491930961609e-10,
                4.65661287307739e-10,
                4.65661287307739e-10,
                32.3504170451779,
                0,
                0,
                0,
                31.1396764498204,
                0,
                0,
                0,
                36.2735965452157
            ]
        },
        "children":[
            {
                "boundingVolume":{
                    "box":[
                        0.442140729632229,
                        0.883671367773786,
                        2.32300778198987,
                        18.1499997093342,
                        0,
                        0,
                        0,
                        11.0719899774995,
                        0,
                        0,
                        0,
                        18.4318225253373
                    ]
                },
                "children":[
                    {
                        "boundingVolume":{
                            "box":[
                                0.442140729632229,
                                0.883671367773786,
                                2.32300778198987,
                                18.1499997093342,
                                0,
                                0,
                                0,
                                11.0719899774995,
                                0,
                                0,
                                0,
                                18.4318225253373
                            ]
                        },
                        "children":[
                            {
                                "boundingVolume":{
                                    "box":[
                                        0.442140729632229,
                                        0.883671367773786,
                                        2.32300778198987,
                                        18.1499997093342,
                                        0,
                                        0,
                                        0,
                                        11.0719899774995,
                                        0,
                                        0,
                                        0,
                                        18.4318225253373
                                    ]
                                },
                                "children":[
                                    {
                                        "boundingVolume":{
                                            "box":[
                                                0.442140729632229,
                                                0.883671367773786,
                                                2.32300778198987,
                                                18.1499997093342,
                                                0,
                                                0,
                                                0,
                                                11.0719899774995,
                                                0,
                                                0,
                                                0,
                                                18.4318225253373
                                            ]
                                        },
                                        "children":[
                                            {
                                                "boundingVolume":{
                                                    "box":[
                                                        0.442140729632229,
                                                        0.883671367773786,
                                                        2.32300778198987,
                                                        18.1499997093342,
                                                        0,
                                                        0,
                                                        0,
                                                        11.0719899774995,
                                                        0,
                                                        0,
                                                        0,
                                                        18.4318225253373
                                                    ]
                                                },
                                                "children":[
                                                    {
                                                        "boundingVolume":{
                                                            "box":[
                                                                0.442140729632229,
                                                                0.883671367773786,
                                                                2.32300778198987,
                                                                18.1499997093342,
                                                                0,
                                                                0,
                                                                0,
                                                                11.0719899774995,
                                                                0,
                                                                0,
                                                                0,
                                                                18.4318225253373
                                                            ]
                                                        },
                                                        "children":[
                                                            {
                                                                "boundingVolume":{
                                                                    "box":[
                                                                        0.442140729632229,
                                                                        0.883671367773786,
                                                                        2.32300778198987,
                                                                        18.1499997093342,
                                                                        0,
                                                                        0,
                                                                        0,
                                                                        11.0719899774995,
                                                                        0,
                                                                        0,
                                                                        0,
                                                                        18.4318225253373
                                                                    ]
                                                                },
                                                                "children":[
                                                                    {
                                                                        "boundingVolume":{
                                                                            "box":[
                                                                                0.442140729632229,
                                                                                0.883671367773786,
                                                                                2.32300778198987,
                                                                                18.1499997093342,
                                                                                0,
                                                                                0,
                                                                                0,
                                                                                11.0719899774995,
                                                                                0,
                                                                                0,
                                                                                0,
                                                                                18.4318225253373
                                                                            ]
                                                                        },
                                                                        "content":{
                                                                            "uri":"0/0/0/0/0/0/0/0/0.b3dm"
                                                                        },
                                                                        "geometricError":0,
                                                                        "refine":"REPLACE",
                                                                        "transform":[
                                                                            1,
                                                                            0,
                                                                            5.55111512312578e-17,
                                                                            0,
                                                                            3.97435433181773e-18,
                                                                            1,
                                                                            -5.55111512312578e-17,
                                                                            0,
                                                                            4.11994255489615e-17,
                                                                            5.55111512312578e-17,
                                                                            1,
                                                                            0,
                                                                            0,
                                                                            0,
                                                                            0,
                                                                            1
                                                                        ]
                                                                    }
                                                                ],
                                                                "content":{
                                                                    "uri":"0/0/0/0/0/0/0/0.b3dm"
                                                                },
                                                                "geometricError":0.909737146925484,
                                                                "refine":"REPLACE",
                                                                "transform":[
                                                                    1,
                                                                    0,
                                                                    5.55111512312578e-17,
                                                                    0,
                                                                    3.97435433181773e-18,
                                                                    1,
                                                                    -5.55111512312578e-17,
                                                                    0,
                                                                    4.11994255489615e-17,
                                                                    5.55111512312578e-17,
                                                                    1,
                                                                    0,
                                                                    0,
                                                                    0,
                                                                    0,
                                                                    1
                                                                ]
                                                            }
                                                        ],
                                                        "content":{
                                                            "uri":"0/0/0/0/0/0/0.b3dm"
                                                        },
                                                        "geometricError":3.63894858770194,
                                                        "refine":"REPLACE",
                                                        "transform":[
                                                            1,
                                                            0,
                                                            5.55111512312578e-17,
                                                            0,
                                                            3.97435433181773e-18,
                                                            1,
                                                            -5.55111512312578e-17,
                                                            0,
                                                            4.11994255489615e-17,
                                                            5.55111512312578e-17,
                                                            1,
                                                            0,
                                                            0,
                                                            0,
                                                            0,
                                                            1
                                                        ]
                                                    }
                                                ],
                                                "content":{
                                                    "uri":"0/0/0/0/0/0.b3dm"
                                                },
                                                "geometricError":14.5557943508077,
                                                "refine":"REPLACE",
                                                "transform":[
                                                    1,
                                                    0,
                                                    5.55111512312578e-17,
                                                    0,
                                                    3.97435433181773e-18,
                                                    1,
                                                    -5.55111512312578e-17,
                                                    0,
                                                    4.11994255489615e-17,
                                                    5.55111512312578e-17,
                                                    1,
                                                    0,
                                                    0,
                                                    0,
                                                    0,
                                                    1
                                                ]
                                            }
                                        ],
                                        "content":{
                                            "uri":"0/0/0/0/0.b3dm"
                                        },
                                        "geometricError":58.223177403231,
                                        "refine":"REPLACE",
                                        "transform":[
                                            1,
                                            0,
                                            5.55111512312578e-17,
                                            0,
                                            3.97435433181773e-18,
                                            1,
                                            -5.55111512312578e-17,
                                            0,
                                            4.11994255489615e-17,
                                            5.55111512312578e-17,
                                            1,
                                            0,
                                            0,
                                            0,
                                            0,
                                            1
                                        ]
                                    }
                                ],
                                "geometricError":232.892709612924,
                                "refine":"REPLACE",
                                "transform":[
                                    1,
                                    0,
                                    5.55111512312578e-17,
                                    0,
                                    3.97435433181773e-18,
                                    1,
                                    -5.55111512312578e-17,
                                    0,
                                    4.11994255489615e-17,
                                    5.55111512312578e-17,
                                    1,
                                    0,
                                    0,
                                    0,
                                    0,
                                    1
                                ]
                            }
                        ],
                        "geometricError":931.570838451695,
                        "refine":"REPLACE",
                        "transform":[
                            1,
                            0,
                            5.55111512312578e-17,
                            0,
                            3.97435433181773e-18,
                            1,
                            -5.55111512312578e-17,
                            0,
                            4.11994255489615e-17,
                            5.55111512312578e-17,
                            1,
                            0,
                            0,
                            0,
                            0,
                            1
                        ]
                    }
                ],
                "geometricError":3726.28335380678,
                "refine":"REPLACE",
                "transform":[
                    1,
                    0,
                    5.55111512312578e-17,
                    0,
                    3.97435433181773e-18,
                    1,
                    -5.55111512312578e-17,
                    0,
                    4.11994255489615e-17,
                    5.55111512312578e-17,
                    1,
                    0,
                    0,
                    0,
                    0,
                    1
                ]
            }
        ],
        "geometricError":3726.28335380678,
        "refine":"REPLACE",
        "transform":[
            -0.852860099376205,
            -0.522139493710263,
            0,
            0,
            0.269233011246452,
            -0.439763885882993,
            0.856808794497499,
            0,
            -0.447373710165425,
            0.730738033621543,
            0.515634259598548,
            0,
            -2850864.77260404,
            4656588.59856402,
            3285851.43211411,
            1
        ]
    }
}