{
    "asset":{
        "generatetool":"cesiumlab@www.cesiumlab.com",
        "gltfUpAxis":"Z",
        "version":"1.0"
    },
    "root":{
        "boundingVolume":{
            "box":[
                0,
                -4.65661287307739e-10,
                0,
                25.684540792834,
                0,
                0,
                0,
                27.0256204381585,
                0,
                0,
                0,
                30.5102636869997
            ]
        },
        "children":[
            {
                "boundingVolume":{
                    "box":[
                        0.271602619672194,
                        0.0125304837711155,
                        1.88794941036031,
                        17.0420044620987,
                        0,
                        0,
                        0,
                        12.7679779343307,
                        0,
                        0,
                        0,
                        11.7240155604668
                    ]
                },
                "children":[
                    {
                        "boundingVolume":{
                            "box":[
                                0.271602619672194,
                                0.0125304837711155,
                                1.88794941036031,
                                17.0420044620987,
                                0,
                                0,
                                0,
                                12.7679779343307,
                                0,
                                0,
                                0,
                                11.7240155604668
                            ]
                        },
                        "children":[
                            {
                                "boundingVolume":{
                                    "box":[
                                        0.271602619672194,
                                        0.0125304837711155,
                                        1.88794941036031,
                                        17.0420044620987,
                                        0,
                                        0,
                                        0,
                                        12.7679779343307,
                                        0,
                                        0,
                                        0,
                                        11.7240155604668
                                    ]
                                },
                                "children":[
                                    {
                                        "boundingVolume":{
                                            "box":[
                                                0.271602619672194,
                                                0.0125304837711155,
                                                1.88794941036031,
                                                17.0420044620987,
                                                0,
                                                0,
                                                0,
                                                12.7679779343307,
                                                0,
                                                0,
                                                0,
                                                11.7240155604668
                                            ]
                                        },
                                        "children":[
                                            {
                                                "boundingVolume":{
                                                    "box":[
                                                        0.271602619672194,
                                                        0.0125304837711155,
                                                        1.88794941036031,
                                                        17.0420044620987,
                                                        0,
                                                        0,
                                                        0,
                                                        12.7679779343307,
                                                        0,
                                                        0,
                                                        0,
                                                        11.7240155604668
                                                    ]
                                                },
                                                "children":[
                                                    {
                                                        "boundingVolume":{
                                                            "box":[
                                                                0.271602619672194,
                                                                0.0125304837711155,
                                                                1.88794941036031,
                                                                17.0420044620987,
                                                                0,
                                                                0,
                                                                0,
                                                                12.7679779343307,
                                                                0,
                                                                0,
                                                                0,
                                                                11.7240155604668
                                                            ]
                                                        },
                                                        "children":[
                                                            {
                                                                "boundingVolume":{
                                                                    "box":[
                                                                        0.271602619672194,
                                                                        0.0125304837711155,
                                                                        1.88794941036031,
                                                                        17.0420044620987,
                                                                        0,
                                                                        0,
                                                                        0,
                                                                        12.7679779343307,
                                                                        0,
                                                                        0,
                                                                        0,
                                                                        11.7240155604668
                                                                    ]
                                                                },
                                                                "children":[
                                                                    {
                                                                        "boundingVolume":{
                                                                            "box":[
                                                                                0.271602619672194,
                                                                                0.0125304837711155,
                                                                                1.88794941036031,
                                                                                17.0420044620987,
                                                                                0,
                                                                                0,
                                                                                0,
                                                                                12.7679779343307,
                                                                                0,
                                                                                0,
                                                                                0,
                                                                                11.7240155604668
                                                                            ]
                                                                        },
                                                                        "content":{
                                                                            "uri":"0/0/0/0/0/0/0/0/0.b3dm"
                                                                        },
                                                                        "geometricError":0,
                                                                        "refine":"REPLACE",
                                                                        "transform":[
                                                                            1,
                                                                            0,
                                                                            5.55111512312578e-17,
                                                                            0,
                                                                            3.97658367127774e-18,
                                                                            1,
                                                                            0,
                                                                            0,
                                                                            -1.43154294334951e-17,
                                                                            5.55111512312578e-17,
                                                                            1,
                                                                            0,
                                                                            0,
                                                                            0,
                                                                            0,
                                                                            1
                                                                        ]
                                                                    }
                                                                ],
                                                                "content":{
                                                                    "uri":"0/0/0/0/0/0/0/0.b3dm"
                                                                },
                                                                "geometricError":0.756603854953845,
                                                                "refine":"REPLACE",
                                                                "transform":[
                                                                    1,
                                                                    0,
                                                                    5.55111512312578e-17,
                                                                    0,
                                                                    3.97658367127774e-18,
                                                                    1,
                                                                    0,
                                                                    0,
                                                                    -1.43154294334951e-17,
                                                                    5.55111512312578e-17,
                                                                    1,
                                                                    0,
                                                                    0,
                                                                    0,
                                                                    0,
                                                                    1
                                                                ]
                                                            }
                                                        ],
                                                        "content":{
                                                            "uri":"0/0/0/0/0/0/0.b3dm"
                                                        },
                                                        "geometricError":3.02641541981538,
                                                        "refine":"REPLACE",
                                                        "transform":[
                                                            1,
                                                            0,
                                                            5.55111512312578e-17,
                                                            0,
                                                            3.97658367127774e-18,
                                                            1,
                                                            0,
                                                            0,
                                                            -1.43154294334951e-17,
                                                            5.55111512312578e-17,
                                                            1,
                                                            0,
                                                            0,
                                                            0,
                                                            0,
                                                            1
                                                        ]
                                                    }
                                                ],
                                                "content":{
                                                    "uri":"0/0/0/0/0/0.b3dm"
                                                },
                                                "geometricError":12.1056616792615,
                                                "refine":"REPLACE",
                                                "transform":[
                                                    1,
                                                    0,
                                                    5.55111512312578e-17,
                                                    0,
                                                    3.97658367127774e-18,
                                                    1,
                                                    0,
                                                    0,
                                                    -1.43154294334951e-17,
                                                    5.55111512312578e-17,
                                                    1,
                                                    0,
                                                    0,
                                                    0,
                                                    0,
                                                    1
                                                ]
                                            }
                                        ],
                                        "content":{
                                            "uri":"0/0/0/0/0.b3dm"
                                        },
                                        "geometricError":48.422646717046,
                                        "refine":"REPLACE",
                                        "transform":[
                                            1,
                                            0,
                                            5.55111512312578e-17,
                                            0,
                                            3.97658367127774e-18,
                                            1,
                                            0,
                                            0,
                                            -1.43154294334951e-17,
                                            5.55111512312578e-17,
                                            1,
                                            0,
                                            0,
                                            0,
                                            0,
                                            1
                                        ]
                                    }
                                ],
                                "content":{
                                    "uri":"0/0/0/0.b3dm"
                                },
                                "geometricError":193.690586868184,
                                "refine":"REPLACE",
                                "transform":[
                                    1,
                                    0,
                                    5.55111512312578e-17,
                                    0,
                                    3.97658367127774e-18,
                                    1,
                                    0,
                                    0,
                                    -1.43154294334951e-17,
                                    5.55111512312578e-17,
                                    1,
                                    0,
                                    0,
                                    0,
                                    0,
                                    1
                                ]
                            }
                        ],
                        "geometricError":774.762347472737,
                        "refine":"REPLACE",
                        "transform":[
                            1,
                            0,
                            5.55111512312578e-17,
                            0,
                            3.97658367127774e-18,
                            1,
                            0,
                            0,
                            -1.43154294334951e-17,
                            5.55111512312578e-17,
                            1,
                            0,
                            0,
                            0,
                            0,
                            1
                        ]
                    }
                ],
                "geometricError":3099.04938989095,
                "refine":"REPLACE",
                "transform":[
                    1,
                    0,
                    5.55111512312578e-17,
                    0,
                    3.97658367127774e-18,
                    1,
                    0,
                    0,
                    -1.43154294334951e-17,
                    5.55111512312578e-17,
                    1,
                    0,
                    0,
                    0,
                    0,
                    1
                ]
            }
        ],
        "geometricError":3099.04938989095,
        "refine":"REPLACE",
        "transform":[
            -0.853042374909847,
            -0.521841648978086,
            0,
            0,
            0.269149067735348,
            -0.439971704817632,
            0.856728474078608,
            0,
            -0.44707659963966,
            0.730825692180905,
            0.515767701298696,
            0,
            -2848967.41474158,
            4657140.5986301,
            3286697.12474435,
            1
        ]
    }
}